functional_extensions/__init__.py
functional_extensions/fe.py
functional_extensions/prototyping.py
functional_extensions/tests.py
funext-0.2.0.dist-info/LICENSE
funext-0.2.0.dist-info/METADATA
funext-0.2.0.dist-info/WHEEL
funext-0.2.0.dist-info/top_level.txt
funext-0.2.0.dist-info/RECORD
