Metadata-Version: 2.1
Name: funext
Version: 0.2.0
Summary: Functional extensions for Python objects
Home-page: https://github.com/ReinhardtJ/Functional-Extensions
Author: Jonas Reinhardt
Author-email: jonas@reinhardt.ai
License: UNKNOWN
Project-URL: Bug Tracker, https://github.com/ReinhardtJ/Functional-Extensions/issues
Platform: UNKNOWN
Classifier: Programming Language :: Python :: 3
Classifier: License :: OSI Approved :: MIT License
Classifier: Operating System :: OS Independent
Requires-Python: >=3.7
Requires-Dist: funcy (>=1.17)
